CHANGES.md
LICENSE
MANIFEST.in
README.md
curlify.py
setup.py
curlify.egg-info/PKG-INFO
curlify.egg-info/SOURCES.txt
curlify.egg-info/dependency_links.txt
curlify.egg-info/requires.txt
curlify.egg-info/top_level.txt