Metadata-Version: 1.1
Name: curlify
Version: 2.0
Summary: Library to convert python requests object to curl command.
Home-page: https://github.com/oeegor/curlify
Author: Egor Orlov
Author-email: oeegor@gmail.com
License: MIT License
Platform: any
Classifier: Environment :: Web Environment
Classifier: Intended Audience :: Developers
Classifier: License :: OSI Approved :: MIT License
Classifier: Operating System :: OS Independent
Classifier: Programming Language :: Python
Classifier: Programming Language :: Python :: 2.7
Classifier: Programming Language :: Python :: 3.5
Classifier: Topic :: Internet :: WWW/HTTP
Classifier: Topic :: Internet :: WWW/HTTP :: Dynamic Content
